k8s_cli/__init__.py
k8s_cli/k8s_cli.py
k8s_cli-1.2.5.dist-info/LICENSE
k8s_cli-1.2.5.dist-info/METADATA
k8s_cli-1.2.5.dist-info/WHEEL
k8s_cli-1.2.5.dist-info/entry_points.txt
k8s_cli-1.2.5.dist-info/top_level.txt
k8s_cli-1.2.5.dist-info/RECORD
