Metadata-Version: 2.1
Name: k8s-cli
Version: 1.2.5
Summary: This Python package provides native Kubernetes CLI aliases, allowing users to manage and query Kubernetes resources directly from Python without using kubectl
Home-page: https://github.com/SCGIS-Wales/kalias
Author: Dejan Gregor
Author-email: developer@cloudfever.uk
Project-URL: Documentation, https://github.com/SCGIS-Wales/kalias#readme
Project-URL: Source, https://github.com/SCGIS-Wales/kalias
Project-URL: Tracker, https://github.com/SCGIS-Wales/kalias/issues
Classifier: Programming Language :: Python :: 3
Classifier: License :: OSI Approved :: MIT License
Classifier: Operating System :: OS Independent
Classifier: Development Status :: 4 - Beta
Classifier: Intended Audience :: Developers
Classifier: Topic :: Software Development :: Libraries :: Python Modules
Requires-Python: >=3.6
License-File: LICENSE
Requires-Dist: click
Requires-Dist: kubernetes
Requires-Dist: prettytable
